MANIFEST.in
README.md
requirements.txt
requirements_test.txt
setup.cfg
setup.py
tests.py
ice_pick/__init__.py
ice_pick/api.py
ice_pick/exceptions.py
ice_pick/groups.py
ice_pick/utils.py
ice_pick.egg-info/PKG-INFO
ice_pick.egg-info/SOURCES.txt
ice_pick.egg-info/dependency_links.txt
ice_pick.egg-info/requires.txt
ice_pick.egg-info/top_level.txt
ice_pick/filters/__init__.py
ice_pick/filters/consolidate.py
ice_pick/filters/group_by.py
ice_pick/filters/operations.py
ice_pick/filters/products.py
ice_pick/filters/regions.py
ice_pick/filters/usage_types.py