Metadata-Version: 1.1
Name: ice-pick
Version: 0.5
Summary: Python data access interface for Netflix OSS Ice Tool
Home-page: https://github.com/demandmedia/ice_pick
Author: Demand Media
Author-email: opensource@demandmedia.com
License: Apache 2.0
Platform: UNKNOWN
Classifier: Development Status :: 5 - Production/Stable
Classifier: Intended Audience :: Developers
Classifier: Natural Language :: English
Classifier: License :: OSI Approved :: Apache Software License
Classifier: Programming Language :: Python
Classifier: Programming Language :: Python :: 2.6
Classifier: Programming Language :: Python :: 2.7
